simple_rate/__init__.py
simple_rate/rate.py
simple_rate-0.1.dist-info/LICENSE
simple_rate-0.1.dist-info/METADATA
simple_rate-0.1.dist-info/WHEEL
simple_rate-0.1.dist-info/top_level.txt
simple_rate-0.1.dist-info/RECORD
